{
  "type": "FeatureCollection", 
  "features": [
       {
      "geometry": {
        "type": "Point", 
        "coordinates": [
		-0.9750332,
        51.1493454
        ]
      }, 
      "type": "Feature", 
      "properties": {
        "category": "Public House", 
        "hours": "12:00 noon - 11:00pm", 
        "description": "Our staff are looking forward to serving you with our new fantastic range of drinks, great offers, delicious menu and events.", 
        "name": "The Bakers Arms",
        "phone": "01420 543867",
        "web": "<a href=\"#680341\" class=\"viewit\">View this Pub</a>"

      }
    }
    
    ]
}